cli/__init__.py
cli/__main__.py
cli/auth.py
cli/common.py
cli/logs.py
cli/memory.py
cli/oauth2.py
cli/profile.py
cli/py.typed
cli/registry.py
cli/spaces.py
cli/tools.py
cli/webhooks.py
heysol/__init__.py
heysol/cli.py
heysol/client.py
heysol/config.json
heysol/config.py
heysol/exceptions.py
heysol/health_check.py
heysol/operations.py
heysol/py.typed
heysol/registry_config.py
heysol/clients/__init__.py
heysol/clients/api_client.py
heysol/clients/mcp_client.py
heysol/models/__init__.py
heysol/models/config.py
heysol/models/requests.py
heysol/models/responses.py
heysol_api_client-1.3.0.dist-info/licenses/LICENSE
heysol_api_client-1.3.0.dist-info/METADATA
heysol_api_client-1.3.0.dist-info/WHEEL
heysol_api_client-1.3.0.dist-info/entry_points.txt
heysol_api_client-1.3.0.dist-info/top_level.txt
heysol_api_client-1.3.0.dist-info/RECORD
