Metadata-Version: 2.4
Name: heysol-api-client
Version: 1.3.0
Summary: A comprehensive Python client for the HeySol API with MCP protocol support, built by Dexter Hadley, MD/PhD
Home-page: https://github.com/HadleyLab/heysol-api-client
Author: Dexter Hadley, MD/PhD
Author-email: "Dexter Hadley, MD/PhD" <iDrDex@HadleyLab.org>
Maintainer-email: HadleyLab <iDrDex@HadleyLab.org>
License: MIT
Project-URL: Homepage, https://github.com/HadleyLab/heysol-api-client
Project-URL: Documentation, https://docs.heysol.ai/api-reference
Project-URL: Repository, https://github.com/HadleyLab/heysol-api-client
Project-URL: Issues, https://github.com/HadleyLab/heysol-api-client/issues
Project-URL: Changelog, https://github.com/HadleyLab/heysol-api-client/blob/main/CHANGELOG.md
Keywords: heysol,api-client,mcp,memory-management,healthcare,clinical-trials,oncology,python
Classifier: Development Status :: 5 - Production/Stable
Classifier: Intended Audience :: Developers
Classifier: Intended Audience :: Healthcare Industry
Classifier: Intended Audience :: Science/Research
Classifier: License :: OSI Approved :: MIT License
Classifier: Operating System :: OS Independent
Classifier: Programming Language :: Python :: 3
Classifier: Programming Language :: Python :: 3.8
Classifier: Programming Language :: Python :: 3.9
Classifier: Programming Language :: Python :: 3.10
Classifier: Programming Language :: Python :: 3.11
Classifier: Programming Language :: Python :: 3.12
Classifier: Topic :: Software Development :: Libraries :: Python Modules
Classifier: Topic :: Scientific/Engineering :: Information Analysis
Classifier: Topic :: Internet :: WWW/HTTP
Requires-Python: >=3.8
License-File: LICENSE
Requires-Dist: requests>=2.25.0
Requires-Dist: aiohttp>=3.8.0
Requires-Dist: python-dotenv>=0.19.0
Requires-Dist: typer>=0.19.0
Requires-Dist: pydantic>=2.0
Provides-Extra: dev
Requires-Dist: pytest>=7.0.0; extra == "dev"
Requires-Dist: pytest-asyncio>=0.21.0; extra == "dev"
Requires-Dist: pytest-cov>=4.0.0; extra == "dev"
Requires-Dist: black>=22.0.0; extra == "dev"
Requires-Dist: isort>=5.10.0; extra == "dev"
Requires-Dist: mypy>=1.0.0; extra == "dev"
Requires-Dist: flake8>=4.0.0; extra == "dev"
Requires-Dist: pre-commit>=2.17.0; extra == "dev"
Provides-Extra: docs
Requires-Dist: sphinx>=4.0.0; extra == "docs"
Requires-Dist: sphinx-rtd-theme>=1.0.0; extra == "docs"
Dynamic: author
Dynamic: home-page
Dynamic: license-file
Dynamic: requires-python
